<?xml version="1.0" ?>
<!DOCTYPE plans SYSTEM "http://www.matsim.org/files/dtd/plans_v4.dtd">
<plans>
<person id="1">
	<plan>
		<act type="h" x="-25000" y="0" link="1" end_time="06:00" />
		<leg mode="car">
			<route>2 7 12</route>
		</leg>
		<act type="w" x="10000" y="0" link="20" dur="00:10" />
		<leg mode="car">
			<route>13 14 15 1</route>
		</leg>
		<act type="h" x="-25000" y="0" link="1" />
	</plan>
</person>
 
<person id="2">
	<plan>
		<act type="h" x="-25000" y="0" link="1" end_time="05:59" />
		<leg mode="car">
			<route>2 7 12</route>
		</leg>
		<act type="w" x="10000" y="0" link="20" dur="02:30" />
		<leg mode="car">
			<route>13 14 15 1</route>
		</leg>
		<act type="h" x="-25000" y="0" link="1" />
	</plan>
</person>

<person id="3">
	<plan>
		<act type="h" x="-25000" y="0" link="1" end_time="05:58:30" />
		<leg mode="car">
			<route>2 7 12</route>
		</leg>
		<act type="w" x="10000" y="0" link="20" dur="01:30" />
		<leg mode="car">
			<route>13 14 15 1</route>
		</leg>
		<act type="h" x="-25000" y="0" link="1" />
	</plan>
</person>

<person id="4">
	<plan>
		<act type="h" x="-25000" y="0" link="1" end_time="05:59:30" />
		<leg mode="car">
			<route>2 7 12</route>
		</leg>
		<act type="w" x="10000" y="0" link="20" dur="02:30" />
		<leg mode="car">
			<route>13 14 15 1</route>
		</leg>
		<act type="h" x="-25000" y="0" link="1" />
	</plan>
</person>

<person id="5">
	<plan>
		<act type="h" x="-25000" y="0" link="1" end_time="06:00" />
		<leg mode="car">
			<route>2 7 12</route>
		</leg>
		<act type="w" x="10000" y="0" link="20" dur="06:30" />
		<leg mode="car">
			<route>13 14 15 1</route>
		</leg>
		<act type="h" x="-25000" y="0" link="1" />
	</plan>
</person>

<person id="6">
	<plan>
		<act type="h" x="-25000" y="0" link="1" end_time="06:00" />
		<leg mode="car">
			<route>2 7 12</route>
		</leg>
		<act type="w" x="10000" y="0" link="20" dur="00:30" />
		<leg mode="car">
			<route>13 14 15 1</route>
		</leg>
		<act type="h" x="-25000" y="0" link="1" />
	</plan>
</person>

<person id="7">
	<plan>
		<act type="h" x="-25000" y="0" link="1" end_time="06:00" />
		<leg mode="car">
			<route>2 7 12</route>
		</leg>
		<act type="w" x="10000" y="0" link="20" dur="00:30" />
		<leg mode="car">
			<route>13 14 15 1</route>
		</leg>
		<act type="h" x="-25000" y="0" link="1" />
	</plan>
</person>

<person id="8">
	<plan>
		<act type="h" x="-25000" y="0" link="1" end_time="06:00" />
		<leg mode="car">
			<route>2 7 12</route>
		</leg>
		<act type="w" x="10000" y="0" link="20" dur="00:30" />
		<leg mode="car">
			<route>13 14 15 1</route>
		</leg>
		<act type="h" x="-25000" y="0" link="1" />
	</plan>
</person>

<person id="9">
	<plan>
		<act type="h" x="-25000" y="0" link="1" end_time="06:00" />
		<leg mode="car">
			<route>2 7 12</route>
		</leg>
		<act type="w" x="10000" y="0" link="20" dur="00:30" />
		<leg mode="car">
			<route>13 14 15 1</route>
		</leg>
		<act type="h" x="-25000" y="0" link="1" />
	</plan>
</person>

<person id="10">
	<plan>
		<act type="h" x="-25000" y="0" link="1" end_time="06:00" />
		<leg mode="car">
			<route>2 7 12</route>
		</leg>
		<act type="w" x="10000" y="0" link="20" dur="00:30" />
		<leg mode="car">
			<route>13 14 15 1</route>
		</leg>
		<act type="h" x="-25000" y="0" link="1" />
	</plan>
</person>
<person id="11">
	<plan>
		<act type="h" x="-25000" y="0" link="1" end_time="06:00" />
		<leg mode="car">
			<route>2 7 12</route>
		</leg>
		<act type="w" x="10000" y="0" link="20" dur="00:30" />
		<leg mode="car">
			<route>13 14 15 1</route>
		</leg>
		<act type="h" x="-25000" y="0" link="1" />
	</plan>
</person>

<person id="12">
	<plan>
		<act type="h" x="-25000" y="0" link="1" end_time="06:00" />
		<leg mode="car">
			<route>2 7 12</route>
		</leg>
		<act type="w" x="10000" y="0" link="20" dur="00:30" />
		<leg mode="car">
			<route>13 14 15 1</route>
		</leg>
		<act type="h" x="-25000" y="0" link="1" />
	</plan>
</person>

<person id="13">
	<plan>
		<act type="h" x="-25000" y="0" link="1" end_time="06:00" />
		<leg mode="car">
			<route>2 7 12</route>
		</leg>
		<act type="w" x="10000" y="0" link="20" dur="00:30" />
		<leg mode="car">
			<route>13 14 15 1</route>
		</leg>
		<act type="h" x="-25000" y="0" link="1" />
	</plan>
</person>

<person id="14">
	<plan>
		<act type="h" x="-25000" y="0" link="1" end_time="06:00" />
		<leg mode="car">
			<route>2 7 12</route>
		</leg>
		<act type="w" x="10000" y="0" link="20" dur="00:30" />
		<leg mode="car">
			<route>13 14 15 1</route>
		</leg>
		<act type="h" x="-25000" y="0" link="1" />
	</plan>
</person>

<person id="15">
	<plan>
		<act type="h" x="-25000" y="0" link="1" end_time="06:00" />
		<leg mode="car">
			<route>2 7 12</route>
		</leg>
		<act type="w" x="10000" y="0" link="20" dur="00:30" />
		<leg mode="car">
			<route>13 14 15 1</route>
		</leg>
		<act type="h" x="-25000" y="0" link="1" />
	</plan>
</person>

<person id="16">
	<plan>
		<act type="h" x="-25000" y="0" link="1" end_time="06:00" />
		<leg mode="car">
			<route>2 7 12</route>
		</leg>
		<act type="w" x="10000" y="0" link="20" dur="00:30" />
		<leg mode="car">
			<route>13 14 15 1</route>
		</leg>
		<act type="h" x="-25000" y="0" link="1" />
	</plan>
</person>

<person id="17">
	<plan>
		<act type="h" x="-25000" y="0" link="1" end_time="06:00" />
		<leg mode="car">
			<route>2 7 12</route>
		</leg>
		<act type="w" x="10000" y="0" link="20" dur="00:30" />
		<leg mode="car">
			<route>13 14 15 1</route>
		</leg>
		<act type="h" x="-25000" y="0" link="1" />
	</plan>
</person>

<person id="18">
	<plan>
		<act type="h" x="-25000" y="0" link="1" end_time="06:00" />
		<leg mode="car">
			<route>2 7 12</route>
		</leg>
		<act type="w" x="10000" y="0" link="20" dur="00:30" />
		<leg mode="car">
			<route>13 14 15 1</route>
		</leg>
		<act type="h" x="-25000" y="0" link="1" />
	</plan>
</person>

<person id="19">
	<plan>
		<act type="h" x="-25000" y="0" link="1" end_time="06:00" />
		<leg mode="car">
			<route>2 7 12</route>
		</leg>
		<act type="w" x="10000" y="0" link="20" dur="00:30" />
		<leg mode="car">
			<route>13 14 15 1</route>
		</leg>
		<act type="h" x="-25000" y="0" link="1" />
	</plan>
</person>

<person id="20">
	<plan>
		<act type="h" x="-25000" y="0" link="1" end_time="06:00" />
		<leg mode="car">
			<route>2 7 12</route>
		</leg>
		<act type="w" x="10000" y="0" link="20" dur="00:30" />
		<leg mode="car">
			<route>13 14 15 1</route>
		</leg>
		<act type="h" x="-25000" y="0" link="1" />
	</plan>
</person>

<person id="21">
	<plan>
		<act type="h" x="-25000" y="0" link="1" end_time="06:00" />
		<leg mode="car">
			<route>2 7 12</route>
		</leg>
		<act type="w" x="10000" y="0" link="20" dur="00:30" />
		<leg mode="car">
			<route>13 14 15 1</route>
		</leg>
		<act type="h" x="-25000" y="0" link="1" />
	</plan>
</person>

<person id="22">
	<plan>
		<act type="h" x="-25000" y="0" link="1" end_time="06:00" />
		<leg mode="car">
			<route>2 7 12</route>
		</leg>
		<act type="w" x="10000" y="0" link="20" dur="00:30" />
		<leg mode="car">
			<route>13 14 15 1</route>
		</leg>
		<act type="h" x="-25000" y="0" link="1" />
	</plan>
</person>

<person id="23">
	<plan>
		<act type="h" x="-25000" y="0" link="1" end_time="06:00" />
		<leg mode="car">
			<route>2 7 12</route>
		</leg>
		<act type="w" x="10000" y="0" link="20" dur="00:30" />
		<leg mode="car">
			<route>13 14 15 1</route>
		</leg>
		<act type="h" x="-25000" y="0" link="1" />
	</plan>
</person>

<person id="24">
	<plan>
		<act type="h" x="-25000" y="0" link="1" end_time="06:00" />
		<leg mode="car">
			<route>2 7 12</route>
		</leg>
		<act type="w" x="10000" y="0" link="20" dur="00:30" />
		<leg mode="car">
			<route>13 14 15 1</route>
		</leg>
		<act type="h" x="-25000" y="0" link="1" />
	</plan>
</person>

<person id="25">
	<plan>
		<act type="h" x="-25000" y="0" link="1" end_time="06:00" />
		<leg mode="car">
			<route>2 7 12</route>
		</leg>
		<act type="w" x="10000" y="0" link="20" dur="00:30" />
		<leg mode="car">
			<route>13 14 15 1</route>
		</leg>
		<act type="h" x="-25000" y="0" link="1" />
	</plan>
</person>

<person id="26">
	<plan>
		<act type="h" x="-25000" y="0" link="1" end_time="06:00" />
		<leg mode="car">
			<route>2 7 12</route>
		</leg>
		<act type="w" x="10000" y="0" link="20" dur="00:30" />
		<leg mode="car">
			<route>13 14 15 1</route>
		</leg>
		<act type="h" x="-25000" y="0" link="1" />
	</plan>
</person>

<person id="27">
	<plan>
		<act type="h" x="-25000" y="0" link="1" end_time="06:00" />
		<leg mode="car">
			<route>2 7 12</route>
		</leg>
		<act type="w" x="10000" y="0" link="20" dur="00:30" />
		<leg mode="car">
			<route>13 14 15 1</route>
		</leg>
		<act type="h" x="-25000" y="0" link="1" />
	</plan>
</person>

<person id="28">
	<plan>
		<act type="h" x="-25000" y="0" link="1" end_time="06:00" />
		<leg mode="car">
			<route>2 7 12</route>
		</leg>
		<act type="w" x="10000" y="0" link="20" dur="00:30" />
		<leg mode="car">
			<route>13 14 15 1</route>
		</leg>
		<act type="h" x="-25000" y="0" link="1" />
	</plan>
</person>

<person id="29">
	<plan>
		<act type="h" x="-25000" y="0" link="1" end_time="06:00" />
		<leg mode="car">
			<route>2 7 12</route>
		</leg>
		<act type="w" x="10000" y="0" link="20" dur="00:30" />
		<leg mode="car">
			<route>13 14 15 1</route>
		</leg>
		<act type="h" x="-25000" y="0" link="1" />
	</plan>
</person>

<person id="30">
	<plan>
		<act type="h" x="-25000" y="0" link="1" end_time="06:00" />
		<leg mode="car">
			<route>2 7 12</route>
		</leg>
		<act type="w" x="10000" y="0" link="20" dur="00:30" />
		<leg mode="car">
			<route>13 14 15 1</route>
		</leg>
		<act type="h" x="-25000" y="0" link="1" />
	</plan>
</person>

<person id="31">
	<plan>
		<act type="h" x="-25000" y="0" link="1" end_time="06:00" />
		<leg mode="car">
			<route>2 7 12</route>
		</leg>
		<act type="w" x="10000" y="0" link="20" dur="00:30" />
		<leg mode="car">
			<route>13 14 15 1</route>
		</leg>
		<act type="h" x="-25000" y="0" link="1" />
	</plan>
</person>

<person id="32">
	<plan>
		<act type="h" x="-25000" y="0" link="1" end_time="06:00" />
		<leg mode="car">
			<route>2 7 12</route>
		</leg>
		<act type="w" x="10000" y="0" link="20" dur="00:30" />
		<leg mode="car">
			<route>13 14 15 1</route>
		</leg>
		<act type="h" x="-25000" y="0" link="1" />
	</plan>
</person>

<person id="33">
	<plan>
		<act type="h" x="-25000" y="0" link="1" end_time="06:00" />
		<leg mode="car">
			<route>2 7 12</route>
		</leg>
		<act type="w" x="10000" y="0" link="20" dur="00:30" />
		<leg mode="car">
			<route>13 14 15 1</route>
		</leg>
		<act type="h" x="-25000" y="0" link="1" />
	</plan>
</person>

<person id="34">
	<plan>
		<act type="h" x="-25000" y="0" link="1" end_time="06:00" />
		<leg mode="car">
			<route>2 7 12</route>
		</leg>
		<act type="w" x="10000" y="0" link="20" dur="00:30" />
		<leg mode="car">
			<route>13 14 15 1</route>
		</leg>
		<act type="h" x="-25000" y="0" link="1" />
	</plan>
</person>

<person id="35">
	<plan>
		<act type="h" x="-25000" y="0" link="1" end_time="06:00" />
		<leg mode="car">
			<route>2 7 12</route>
		</leg>
		<act type="w" x="10000" y="0" link="20" dur="00:30" />
		<leg mode="car">
			<route>13 14 15 1</route>
		</leg>
		<act type="h" x="-25000" y="0" link="1" />
	</plan>
</person>

<person id="36">
	<plan>
		<act type="h" x="-25000" y="0" link="1" end_time="06:00" />
		<leg mode="car">
			<route>2 7 12</route>
		</leg>
		<act type="w" x="10000" y="0" link="20" dur="00:30" />
		<leg mode="car">
			<route>13 14 15 1</route>
		</leg>
		<act type="h" x="-25000" y="0" link="1" />
	</plan>
</person>

<person id="37">
	<plan>
		<act type="h" x="-25000" y="0" link="1" end_time="06:00" />
		<leg mode="car">
			<route>2 7 12</route>
		</leg>
		<act type="w" x="10000" y="0" link="20" dur="00:30" />
		<leg mode="car">
			<route>13 14 15 1</route>
		</leg>
		<act type="h" x="-25000" y="0" link="1" />
	</plan>
</person>

<person id="38">
	<plan>
		<act type="h" x="-25000" y="0" link="1" end_time="06:00" />
		<leg mode="car">
			<route>2 7 12</route>
		</leg>
		<act type="w" x="10000" y="0" link="20" dur="00:30" />
		<leg mode="car">
			<route>13 14 15 1</route>
		</leg>
		<act type="h" x="-25000" y="0" link="1" />
	</plan>
</person>

<person id="39">
	<plan>
		<act type="h" x="-25000" y="0" link="1" end_time="06:00" />
		<leg mode="car">
			<route>2 7 12</route>
		</leg>
		<act type="w" x="10000" y="0" link="20" dur="00:30" />
		<leg mode="car">
			<route>13 14 15 1</route>
		</leg>
		<act type="h" x="-25000" y="0" link="1" />
	</plan>
</person>

<person id="40">
	<plan>
		<act type="h" x="-25000" y="0" link="1" end_time="06:00" />
		<leg mode="car">
			<route>2 7 12</route>
		</leg>
		<act type="w" x="10000" y="0" link="20" dur="00:30" />
		<leg mode="car">
			<route>13 14 15 1</route>
		</leg>
		<act type="h" x="-25000" y="0" link="1" />
	</plan>
</person>

<person id="41">
	<plan>
		<act type="h" x="-25000" y="0" link="1" end_time="06:00" />
		<leg mode="car">
			<route>2 7 12</route>
		</leg>
		<act type="w" x="10000" y="0" link="20" dur="00:30" />
		<leg mode="car">
			<route>13 14 15 1</route>
		</leg>
		<act type="h" x="-25000" y="0" link="1" />
	</plan>
</person>

<person id="42">
	<plan>
		<act type="h" x="-25000" y="0" link="1" end_time="06:00" />
		<leg mode="car">
			<route>2 7 12</route>
		</leg>
		<act type="w" x="10000" y="0" link="20" dur="00:30" />
		<leg mode="car">
			<route>13 14 15 1</route>
		</leg>
		<act type="h" x="-25000" y="0" link="1" />
	</plan>
</person>

<person id="43">
	<plan>
		<act type="h" x="-25000" y="0" link="1" end_time="06:00" />
		<leg mode="car">
			<route>2 7 12</route>
		</leg>
		<act type="w" x="10000" y="0" link="20" dur="00:30" />
		<leg mode="car">
			<route>13 14 15 1</route>
		</leg>
		<act type="h" x="-25000" y="0" link="1" />
	</plan>
</person>

<person id="44">
	<plan>
		<act type="h" x="-25000" y="0" link="1" end_time="06:00" />
		<leg mode="car">
			<route>2 7 12</route>
		</leg>
		<act type="w" x="10000" y="0" link="20" dur="00:30" />
		<leg mode="car">
			<route>13 14 15 1</route>
		</leg>
		<act type="h" x="-25000" y="0" link="1" />
	</plan>
</person>

<person id="45">
	<plan>
		<act type="h" x="-25000" y="0" link="1" end_time="06:00" />
		<leg mode="car">
			<route>2 7 12</route>
		</leg>
		<act type="w" x="10000" y="0" link="20" dur="00:30" />
		<leg mode="car">
			<route>13 14 15 1</route>
		</leg>
		<act type="h" x="-25000" y="0" link="1" />
	</plan>
</person>

<person id="46">
	<plan>
		<act type="h" x="-25000" y="0" link="1" end_time="06:00" />
		<leg mode="car">
			<route>2 7 12</route>
		</leg>
		<act type="w" x="10000" y="0" link="20" dur="00:30" />
		<leg mode="car">
			<route>13 14 15 1</route>
		</leg>
		<act type="h" x="-25000" y="0" link="1" />
	</plan>
</person>

<person id="47">
	<plan>
		<act type="h" x="-25000" y="0" link="1" end_time="06:00" />
		<leg mode="car">
			<route>2 7 12</route>
		</leg>
		<act type="w" x="10000" y="0" link="20" dur="00:30" />
		<leg mode="car">
			<route>13 14 15 1</route>
		</leg>
		<act type="h" x="-25000" y="0" link="1" />
	</plan>
</person>

<person id="48">
	<plan>
		<act type="h" x="-25000" y="0" link="1" end_time="06:00" />
		<leg mode="car">
			<route>2 7 12</route>
		</leg>
		<act type="w" x="10000" y="0" link="20" dur="00:30" />
		<leg mode="car">
			<route>13 14 15 1</route>
		</leg>
		<act type="h" x="-25000" y="0" link="1" />
	</plan>
</person>

<person id="49">
	<plan>
		<act type="h" x="-25000" y="0" link="1" end_time="06:00" />
		<leg mode="car">
			<route>2 7 12</route>
		</leg>
		<act type="w" x="10000" y="0" link="20" dur="00:30" />
		<leg mode="car">
			<route>13 14 15 1</route>
		</leg>
		<act type="h" x="-25000" y="0" link="1" />
	</plan>
</person>

<person id="50">
	<plan>
		<act type="h" x="-25000" y="0" link="1" end_time="06:00" />
		<leg mode="car">
			<route>2 7 12</route>
		</leg>
		<act type="w" x="10000" y="0" link="20" dur="00:30" />
		<leg mode="car">
			<route>13 14 15 1</route>
		</leg>
		<act type="h" x="-25000" y="0" link="1" />
	</plan>
</person>

<person id="51">
	<plan>
		<act type="h" x="-25000" y="0" link="1" end_time="06:00" />
		<leg mode="car">
			<route>2 7 12</route>
		</leg>
		<act type="w" x="10000" y="0" link="20" dur="00:30" />
		<leg mode="car">
			<route>13 14 15 1</route>
		</leg>
		<act type="h" x="-25000" y="0" link="1" />
	</plan>
</person>

<person id="52">
	<plan>
		<act type="h" x="-25000" y="0" link="1" end_time="06:00" />
		<leg mode="car">
			<route>2 7 12</route>
		</leg>
		<act type="w" x="10000" y="0" link="20" dur="00:30" />
		<leg mode="car">
			<route>13 14 15 1</route>
		</leg>
		<act type="h" x="-25000" y="0" link="1" />
	</plan>
</person>

<person id="53">
	<plan>
		<act type="h" x="-25000" y="0" link="1" end_time="06:00" />
		<leg mode="car">
			<route>2 7 12</route>
		</leg>
		<act type="w" x="10000" y="0" link="20" dur="00:30" />
		<leg mode="car">
			<route>13 14 15 1</route>
		</leg>
		<act type="h" x="-25000" y="0" link="1" />
	</plan>
</person>

<person id="54">
	<plan>
		<act type="h" x="-25000" y="0" link="1" end_time="06:00" />
		<leg mode="car">
			<route>2 7 12</route>
		</leg>
		<act type="w" x="10000" y="0" link="20" dur="00:30" />
		<leg mode="car">
			<route>13 14 15 1</route>
		</leg>
		<act type="h" x="-25000" y="0" link="1" />
	</plan>
</person>

<person id="55">
	<plan>
		<act type="h" x="-25000" y="0" link="1" end_time="06:00" />
		<leg mode="car">
			<route>2 7 12</route>
		</leg>
		<act type="w" x="10000" y="0" link="20" dur="00:30" />
		<leg mode="car">
			<route>13 14 15 1</route>
		</leg>
		<act type="h" x="-25000" y="0" link="1" />
	</plan>
</person>

<person id="56">
	<plan>
		<act type="h" x="-25000" y="0" link="1" end_time="06:00" />
		<leg mode="car">
			<route>2 7 12</route>
		</leg>
		<act type="w" x="10000" y="0" link="20" dur="00:30" />
		<leg mode="car">
			<route>13 14 15 1</route>
		</leg>
		<act type="h" x="-25000" y="0" link="1" />
	</plan>
</person>

<person id="57">
	<plan>
		<act type="h" x="-25000" y="0" link="1" end_time="06:00" />
		<leg mode="car">
			<route>2 7 12</route>
		</leg>
		<act type="w" x="10000" y="0" link="20" dur="00:30" />
		<leg mode="car">
			<route>13 14 15 1</route>
		</leg>
		<act type="h" x="-25000" y="0" link="1" />
	</plan>
</person>

<person id="58">
	<plan>
		<act type="h" x="-25000" y="0" link="1" end_time="06:00" />
		<leg mode="car">
			<route>2 7 12</route>
		</leg>
		<act type="w" x="10000" y="0" link="20" dur="00:30" />
		<leg mode="car">
			<route>13 14 15 1</route>
		</leg>
		<act type="h" x="-25000" y="0" link="1" />
	</plan>
</person>

<person id="59">
	<plan>
		<act type="h" x="-25000" y="0" link="1" end_time="06:00" />
		<leg mode="car">
			<route>2 7 12</route>
		</leg>
		<act type="w" x="10000" y="0" link="20" dur="00:30" />
		<leg mode="car">
			<route>13 14 15 1</route>
		</leg>
		<act type="h" x="-25000" y="0" link="1" />
	</plan>
</person>

<person id="60">
	<plan>
		<act type="h" x="-25000" y="0" link="1" end_time="06:00" />
		<leg mode="car">
			<route>2 7 12</route>
		</leg>
		<act type="w" x="10000" y="0" link="20" dur="00:30" />
		<leg mode="car">
			<route>13 14 15 1</route>
		</leg>
		<act type="h" x="-25000" y="0" link="1" />
	</plan>
</person>

<person id="61">
	<plan>
		<act type="h" x="-25000" y="0" link="1" end_time="06:00" />
		<leg mode="car">
			<route>2 7 12</route>
		</leg>
		<act type="w" x="10000" y="0" link="20" dur="00:30" />
		<leg mode="car">
			<route>13 14 15 1</route>
		</leg>
		<act type="h" x="-25000" y="0" link="1" />
	</plan>
</person>

<person id="62">
	<plan>
		<act type="h" x="-25000" y="0" link="1" end_time="06:00" />
		<leg mode="car">
			<route>2 7 12</route>
		</leg>
		<act type="w" x="10000" y="0" link="20" dur="00:30" />
		<leg mode="car">
			<route>13 14 15 1</route>
		</leg>
		<act type="h" x="-25000" y="0" link="1" />
	</plan>
</person>

<person id="63">
	<plan>
		<act type="h" x="-25000" y="0" link="1" end_time="06:00" />
		<leg mode="car">
			<route>2 7 12</route>
		</leg>
		<act type="w" x="10000" y="0" link="20" dur="00:30" />
		<leg mode="car">
			<route>13 14 15 1</route>
		</leg>
		<act type="h" x="-25000" y="0" link="1" />
	</plan>
</person>

<person id="64">
	<plan>
		<act type="h" x="-25000" y="0" link="1" end_time="06:00" />
		<leg mode="car">
			<route>2 7 12</route>
		</leg>
		<act type="w" x="10000" y="0" link="20" dur="00:30" />
		<leg mode="car">
			<route>13 14 15 1</route>
		</leg>
		<act type="h" x="-25000" y="0" link="1" />
	</plan>
</person>

<person id="65">
	<plan>
		<act type="h" x="-25000" y="0" link="1" end_time="06:00" />
		<leg mode="car">
			<route>2 7 12</route>
		</leg>
		<act type="w" x="10000" y="0" link="20" dur="00:30" />
		<leg mode="car">
			<route>13 14 15 1</route>
		</leg>
		<act type="h" x="-25000" y="0" link="1" />
	</plan>
</person>

<person id="66">
	<plan>
		<act type="h" x="-25000" y="0" link="1" end_time="06:00" />
		<leg mode="car">
			<route>2 7 12</route>
		</leg>
		<act type="w" x="10000" y="0" link="20" dur="00:30" />
		<leg mode="car">
			<route>13 14 15 1</route>
		</leg>
		<act type="h" x="-25000" y="0" link="1" />
	</plan>
</person>

<person id="67">
	<plan>
		<act type="h" x="-25000" y="0" link="1" end_time="06:00" />
		<leg mode="car">
			<route>2 7 12</route>
		</leg>
		<act type="w" x="10000" y="0" link="20" dur="00:30" />
		<leg mode="car">
			<route>13 14 15 1</route>
		</leg>
		<act type="h" x="-25000" y="0" link="1" />
	</plan>
</person>

<person id="68">
	<plan>
		<act type="h" x="-25000" y="0" link="1" end_time="06:00" />
		<leg mode="car">
			<route>2 7 12</route>
		</leg>
		<act type="w" x="10000" y="0" link="20" dur="00:30" />
		<leg mode="car">
			<route>13 14 15 1</route>
		</leg>
		<act type="h" x="-25000" y="0" link="1" />
	</plan>
</person>

<person id="69">
	<plan>
		<act type="h" x="-25000" y="0" link="1" end_time="06:00" />
		<leg mode="car">
			<route>2 7 12</route>
		</leg>
		<act type="w" x="10000" y="0" link="20" dur="00:30" />
		<leg mode="car">
			<route>13 14 15 1</route>
		</leg>
		<act type="h" x="-25000" y="0" link="1" />
	</plan>
</person>

<person id="70">
	<plan>
		<act type="h" x="-25000" y="0" link="1" end_time="06:00" />
		<leg mode="car">
			<route>2 7 12</route>
		</leg>
		<act type="w" x="10000" y="0" link="20" dur="00:30" />
		<leg mode="car">
			<route>13 14 15 1</route>
		</leg>
		<act type="h" x="-25000" y="0" link="1" />
	</plan>
</person>

<person id="71">
	<plan>
		<act type="h" x="-25000" y="0" link="1" end_time="06:00" />
		<leg mode="car">
			<route>2 7 12</route>
		</leg>
		<act type="w" x="10000" y="0" link="20" dur="00:30" />
		<leg mode="car">
			<route>13 14 15 1</route>
		</leg>
		<act type="h" x="-25000" y="0" link="1" />
	</plan>
</person>

<person id="72">
	<plan>
		<act type="h" x="-25000" y="0" link="1" end_time="06:00" />
		<leg mode="car">
			<route>2 7 12</route>
		</leg>
		<act type="w" x="10000" y="0" link="20" dur="00:30" />
		<leg mode="car">
			<route>13 14 15 1</route>
		</leg>
		<act type="h" x="-25000" y="0" link="1" />
	</plan>
</person>

<person id="73">
	<plan>
		<act type="h" x="-25000" y="0" link="1" end_time="06:00" />
		<leg mode="car">
			<route>2 7 12</route>
		</leg>
		<act type="w" x="10000" y="0" link="20" dur="00:30" />
		<leg mode="car">
			<route>13 14 15 1</route>
		</leg>
		<act type="h" x="-25000" y="0" link="1" />
	</plan>
</person>

<person id="74">
	<plan>
		<act type="h" x="-25000" y="0" link="1" end_time="06:00" />
		<leg mode="car">
			<route>2 7 12</route>
		</leg>
		<act type="w" x="10000" y="0" link="20" dur="00:30" />
		<leg mode="car">
			<route>13 14 15 1</route>
		</leg>
		<act type="h" x="-25000" y="0" link="1" />
	</plan>
</person>

<person id="75">
	<plan>
		<act type="h" x="-25000" y="0" link="1" end_time="06:00" />
		<leg mode="car">
			<route>2 7 12</route>
		</leg>
		<act type="w" x="10000" y="0" link="20" dur="00:30" />
		<leg mode="car">
			<route>13 14 15 1</route>
		</leg>
		<act type="h" x="-25000" y="0" link="1" />
	</plan>
</person>

<person id="76">
	<plan>
		<act type="h" x="-25000" y="0" link="1" end_time="06:00" />
		<leg mode="car">
			<route>2 7 12</route>
		</leg>
		<act type="w" x="10000" y="0" link="20" dur="00:30" />
		<leg mode="car">
			<route>13 14 15 1</route>
		</leg>
		<act type="h" x="-25000" y="0" link="1" />
	</plan>
</person>

<person id="77">
	<plan>
		<act type="h" x="-25000" y="0" link="1" end_time="06:00" />
		<leg mode="car">
			<route>2 7 12</route>
		</leg>
		<act type="w" x="10000" y="0" link="20" dur="00:30" />
		<leg mode="car">
			<route>13 14 15 1</route>
		</leg>
		<act type="h" x="-25000" y="0" link="1" />
	</plan>
</person>

<person id="78">
	<plan>
		<act type="h" x="-25000" y="0" link="1" end_time="06:00" />
		<leg mode="car">
			<route>2 7 12</route>
		</leg>
		<act type="w" x="10000" y="0" link="20" dur="00:30" />
		<leg mode="car">
			<route>13 14 15 1</route>
		</leg>
		<act type="h" x="-25000" y="0" link="1" />
	</plan>
</person>

<person id="79">
	<plan>
		<act type="h" x="-25000" y="0" link="1" end_time="06:00" />
		<leg mode="car">
			<route>2 7 12</route>
		</leg>
		<act type="w" x="10000" y="0" link="20" dur="00:30" />
		<leg mode="car">
			<route>13 14 15 1</route>
		</leg>
		<act type="h" x="-25000" y="0" link="1" />
	</plan>
</person>

<person id="80">
	<plan>
		<act type="h" x="-25000" y="0" link="1" end_time="06:00" />
		<leg mode="car">
			<route>2 7 12</route>
		</leg>
		<act type="w" x="10000" y="0" link="20" dur="00:30" />
		<leg mode="car">
			<route>13 14 15 1</route>
		</leg>
		<act type="h" x="-25000" y="0" link="1" />
	</plan>
</person>

<person id="81">
	<plan>
		<act type="h" x="-25000" y="0" link="1" end_time="06:00" />
		<leg mode="car">
			<route>2 7 12</route>
		</leg>
		<act type="w" x="10000" y="0" link="20" dur="00:30" />
		<leg mode="car">
			<route>13 14 15 1</route>
		</leg>
		<act type="h" x="-25000" y="0" link="1" />
	</plan>
</person>

<person id="82">
	<plan>
		<act type="h" x="-25000" y="0" link="1" end_time="06:00" />
		<leg mode="car">
			<route>2 7 12</route>
		</leg>
		<act type="w" x="10000" y="0" link="20" dur="00:30" />
		<leg mode="car">
			<route>13 14 15 1</route>
		</leg>
		<act type="h" x="-25000" y="0" link="1" />
	</plan>
</person>

<person id="83">
	<plan>
		<act type="h" x="-25000" y="0" link="1" end_time="06:00" />
		<leg mode="car">
			<route>2 7 12</route>
		</leg>
		<act type="w" x="10000" y="0" link="20" dur="00:30" />
		<leg mode="car">
			<route>13 14 15 1</route>
		</leg>
		<act type="h" x="-25000" y="0" link="1" />
	</plan>
</person>

<person id="84">
	<plan>
		<act type="h" x="-25000" y="0" link="1" end_time="06:00" />
		<leg mode="car">
			<route>2 7 12</route>
		</leg>
		<act type="w" x="10000" y="0" link="20" dur="00:30" />
		<leg mode="car">
			<route>13 14 15 1</route>
		</leg>
		<act type="h" x="-25000" y="0" link="1" />
	</plan>
</person>

<person id="85">
	<plan>
		<act type="h" x="-25000" y="0" link="1" end_time="06:00" />
		<leg mode="car">
			<route>2 7 12</route>
		</leg>
		<act type="w" x="10000" y="0" link="20" dur="00:30" />
		<leg mode="car">
			<route>13 14 15 1</route>
		</leg>
		<act type="h" x="-25000" y="0" link="1" />
	</plan>
</person>

<person id="86">
	<plan>
		<act type="h" x="-25000" y="0" link="1" end_time="06:00" />
		<leg mode="car">
			<route>2 7 12</route>
		</leg>
		<act type="w" x="10000" y="0" link="20" dur="00:30" />
		<leg mode="car">
			<route>13 14 15 1</route>
		</leg>
		<act type="h" x="-25000" y="0" link="1" />
	</plan>
</person>

<person id="87">
	<plan>
		<act type="h" x="-25000" y="0" link="1" end_time="06:00" />
		<leg mode="car">
			<route>2 7 12</route>
		</leg>
		<act type="w" x="10000" y="0" link="20" dur="00:30" />
		<leg mode="car">
			<route>13 14 15 1</route>
		</leg>
		<act type="h" x="-25000" y="0" link="1" />
	</plan>
</person>

<person id="88">
	<plan>
		<act type="h" x="-25000" y="0" link="1" end_time="06:00" />
		<leg mode="car">
			<route>2 7 12</route>
		</leg>
		<act type="w" x="10000" y="0" link="20" dur="00:30" />
		<leg mode="car">
			<route>13 14 15 1</route>
		</leg>
		<act type="h" x="-25000" y="0" link="1" />
	</plan>
</person>

<person id="89">
	<plan>
		<act type="h" x="-25000" y="0" link="1" end_time="06:00" />
		<leg mode="car">
			<route>2 7 12</route>
		</leg>
		<act type="w" x="10000" y="0" link="20" dur="00:30" />
		<leg mode="car">
			<route>13 14 15 1</route>
		</leg>
		<act type="h" x="-25000" y="0" link="1" />
	</plan>
</person>

<person id="90">
	<plan>
		<act type="h" x="-25000" y="0" link="1" end_time="06:00" />
		<leg mode="car">
			<route>2 7 12</route>
		</leg>
		<act type="w" x="10000" y="0" link="20" dur="00:30" />
		<leg mode="car">
			<route>13 14 15 1</route>
		</leg>
		<act type="h" x="-25000" y="0" link="1" />
	</plan>
</person>

<person id="91">
	<plan>
		<act type="h" x="-25000" y="0" link="1" end_time="06:00" />
		<leg mode="car">
			<route>2 7 12</route>
		</leg>
		<act type="w" x="10000" y="0" link="20" dur="00:30" />
		<leg mode="car">
			<route>13 14 15 1</route>
		</leg>
		<act type="h" x="-25000" y="0" link="1" />
	</plan>
</person>

<person id="92">
	<plan>
		<act type="h" x="-25000" y="0" link="1" end_time="06:00" />
		<leg mode="car">
			<route>2 7 12</route>
		</leg>
		<act type="w" x="10000" y="0" link="20" dur="00:30" />
		<leg mode="car">
			<route>13 14 15 1</route>
		</leg>
		<act type="h" x="-25000" y="0" link="1" />
	</plan>
</person>

<person id="93">
	<plan>
		<act type="h" x="-25000" y="0" link="1" end_time="06:00" />
		<leg mode="car">
			<route>2 7 12</route>
		</leg>
		<act type="w" x="10000" y="0" link="20" dur="00:30" />
		<leg mode="car">
			<route>13 14 15 1</route>
		</leg>
		<act type="h" x="-25000" y="0" link="1" />
	</plan>
</person>

<person id="94">
	<plan>
		<act type="h" x="-25000" y="0" link="1" end_time="06:00" />
		<leg mode="car">
			<route>2 7 12</route>
		</leg>
		<act type="w" x="10000" y="0" link="20" dur="00:30" />
		<leg mode="car">
			<route>13 14 15 1</route>
		</leg>
		<act type="h" x="-25000" y="0" link="1" />
	</plan>
</person>

<person id="95">
	<plan>
		<act type="h" x="-25000" y="0" link="1" end_time="06:00" />
		<leg mode="car">
			<route>2 7 12</route>
		</leg>
		<act type="w" x="10000" y="0" link="20" dur="00:30" />
		<leg mode="car">
			<route>13 14 15 1</route>
		</leg>
		<act type="h" x="-25000" y="0" link="1" />
	</plan>
</person>

<person id="96">
	<plan>
		<act type="h" x="-25000" y="0" link="1" end_time="06:00" />
		<leg mode="car">
			<route>2 7 12</route>
		</leg>
		<act type="w" x="10000" y="0" link="20" dur="00:30" />
		<leg mode="car">
			<route>13 14 15 1</route>
		</leg>
		<act type="h" x="-25000" y="0" link="1" />
	</plan>
</person>

<person id="97">
	<plan>
		<act type="h" x="-25000" y="0" link="1" end_time="06:00" />
		<leg mode="car">
			<route>2 7 12</route>
		</leg>
		<act type="w" x="10000" y="0" link="20" dur="00:30" />
		<leg mode="car">
			<route>13 14 15 1</route>
		</leg>
		<act type="h" x="-25000" y="0" link="1" />
	</plan>
</person>

<person id="98">
	<plan>
		<act type="h" x="-25000" y="0" link="1" end_time="06:00" />
		<leg mode="car">
			<route>2 7 12</route>
		</leg>
		<act type="w" x="10000" y="0" link="20" dur="00:30" />
		<leg mode="car">
			<route>13 14 15 1</route>
		</leg>
		<act type="h" x="-25000" y="0" link="1" />
	</plan>
</person>

<person id="99">
	<plan>
		<act type="h" x="-25000" y="0" link="1" end_time="06:00" />
		<leg mode="car">
			<route>2 7 12</route>
		</leg>
		<act type="w" x="10000" y="0" link="20" dur="00:30" />
		<leg mode="car">
			<route>13 14 15 1</route>
		</leg>
		<act type="h" x="-25000" y="0" link="1" />
	</plan>
</person>

<person id="100">
	<plan>
		<act type="h" x="-25000" y="0" link="1" end_time="06:00" />
		<leg mode="car">
			<route>2 7 12</route>
		</leg>
		<act type="w" x="10000" y="0" link="20" dur="00:30" />
		<leg mode="car">
			<route>13 14 15 1</route>
		</leg>
		<act type="h" x="-25000" y="0" link="1" />
	</plan>
</person>

</plans>
